liteindex/__init__.py
liteindex/common_utils.py
liteindex/defined_index.py
liteindex/defined_serializers.py
liteindex/function_cache.py
liteindex/kv_index.py
liteindex/kv_index_utils.py
liteindex/query_parser.py
liteindex-0.0.3.3.dist-info/LICENSE
liteindex-0.0.3.3.dist-info/METADATA
liteindex-0.0.3.3.dist-info/WHEEL
liteindex-0.0.3.3.dist-info/entry_points.txt
liteindex-0.0.3.3.dist-info/top_level.txt
liteindex-0.0.3.3.dist-info/RECORD
