Metadata-Version: 2.1
Name: liteindex
Version: 0.0.3.3
Summary: SQLite based queryable python indexes for dicts and lists
Home-page: https://github.com/notAI-tech/liteindex
Author: BEDAPUDI PRANEETH
Author-email: praneeth@bpraneeth.com
License: MIT
Classifier: License :: OSI Approved :: MIT License
Classifier: Programming Language :: Python
Classifier: Programming Language :: Python :: 3
Classifier: Programming Language :: Python :: 3.6
Classifier: Programming Language :: Python :: Implementation :: CPython
Requires-Python: >=3.6.0
License-File: LICENSE
Provides-Extra: all
Requires-Dist: zstandard; extra == "all"
Requires-Dist: vectorlite-py; extra == "all"
Requires-Dist: numpy; extra == "all"
